LICENSE
MANIFEST.in
README.rst
setup.py
eventlet_log/__init__.py
eventlet_log/simple.py
eventlet_log.egg-info/PKG-INFO
eventlet_log.egg-info/SOURCES.txt
eventlet_log.egg-info/dependency_links.txt
eventlet_log.egg-info/requires.txt
eventlet_log.egg-info/top_level.txt