Metadata-Version: 1.1
Name: eventlet-log
Version: 0.0.3
Summary: Damn simple logging wrapper compatible with eventlet.
Home-page: https://github.com/little-arhat/eventlet_log
Author: Roma Sokolov
Author-email: sokolov.r.v@gmail.com
License: MIT
Platform: UNKNOWN
Classifier: Development Status :: 3 - Alpha
Classifier: Intended Audience :: Developers
Classifier: Natural Language :: English
Classifier: License :: OSI Approved :: MIT License
Classifier: Programming Language :: Python
Classifier: Programming Language :: Python :: 2.6
Classifier: Programming Language :: Python :: 2.7
